quickapi/__init__.py
quickapi/api.py
quickapi/client.py
quickapi/exceptions.py
quickapi/http_clients/__init__.py
quickapi/http_clients/base.py
quickapi/http_clients/httpx.py
quickapi/http_clients/requests.py
quickapi/http_clients/types.py
quickapi/serializers/__init__.py
quickapi/serializers/attrs.py
quickapi/serializers/base.py
quickapi/serializers/dataclass.py
quickapi/serializers/msgspec.py
quickapi/serializers/pydantic.py
quickapi/serializers/types.py
quickapiclient-0.5.1.dist-info/METADATA
quickapiclient-0.5.1.dist-info/WHEEL
quickapiclient-0.5.1.dist-info/licenses/LICENSE
quickapiclient-0.5.1.dist-info/RECORD
