Metadata-Version: 2.4
Name: quickapiclient
Version: 0.5.1
Summary: Create fully typed declarative API clients quickly and easily. 
Author-email: Martin <martinn@users.noreply.github.com>
License-File: LICENSE
Requires-Python: <4.0,>=3.10
Requires-Dist: chili<3.0.0,>=2.8.4
Requires-Dist: httpx<1.0.0,>=0.27.0
Requires-Dist: typing-extensions<5,>=4; python_version < '3.11'
Provides-Extra: attrs
Requires-Dist: attrs<24.0.0,>=23.2.0; extra == 'attrs'
Requires-Dist: cattrs<24.0.0,>=23.2.3; extra == 'attrs'
Provides-Extra: msgspec
Requires-Dist: msgspec<1.0.0,>=0.18.6; extra == 'msgspec'
Provides-Extra: pydantic
Requires-Dist: pydantic<3.0.0,>=2.6.4; extra == 'pydantic'
Provides-Extra: requests
Requires-Dist: requests<3.0.0,>=2.31.0; extra == 'requests'
